README.md
setup.py
dbr_coating/ABCD_matrix.py
dbr_coating/__init__.py
dbr_coating/stack.py
dbr_coating.egg-info/PKG-INFO
dbr_coating.egg-info/SOURCES.txt
dbr_coating.egg-info/dependency_links.txt
dbr_coating.egg-info/not-zip-safe
dbr_coating.egg-info/top_level.txt