Metadata-Version: 1.0
Name: dbr-coating
Version: 0.1
Summary: Distributed Bragg reflector calculator
Home-page: UNKNOWN
Author: Olivier Gobron
Author-email: gobron.olivier@gmail.com
License: UNKNOWN
Platform: UNKNOWN
